staged_script/__init__.py
staged_script/py.typed
staged_script/staged_script.py
staged_script-2.0.5.dist-info/METADATA
staged_script-2.0.5.dist-info/WHEEL
staged_script-2.0.5.dist-info/licenses/LICENSE.md
staged_script-2.0.5.dist-info/RECORD
