Metadata-Version: 2.4
Name: staged-script
Version: 2.0.5
Summary: A Python package enabling the development of robust automation scripts that are subdivided into stages.
License: LICENSE.md
License-File: LICENSE.md
Keywords: automation,command,execution,repeatability,replicability,reproducibility,pipeline,retry,scripting,shell,stages
Author: Jason M. Gates
Author-email: jmgate@sandia.gov
Requires-Python: >=3.10
Classifier: Development Status :: 5 - Production/Stable
Classifier: Intended Audience :: Developers
Classifier: Intended Audience :: Information Technology
Classifier: Intended Audience :: System Administrators
Classifier: License :: OSI Approved :: BSD License
Classifier: License :: Other/Proprietary License
Classifier: Natural Language :: English
Classifier: Operating System :: OS Independent
Classifier: Programming Language :: Python :: 3
Classifier: Programming Language :: Python :: 3.10
Classifier: Programming Language :: Python :: 3.11
Classifier: Programming Language :: Python :: 3.12
Classifier: Programming Language :: Python :: 3.13
Classifier: Programming Language :: Python :: 3.14
Classifier: Programming Language :: Python :: 3 :: Only
Classifier: Topic :: Software Development
Classifier: Topic :: Software Development :: Debuggers
Classifier: Topic :: Software Development :: Documentation
Classifier: Topic :: Software Development :: User Interfaces
Classifier: Topic :: System :: Shells
Classifier: Topic :: System :: System Shells
Classifier: Typing :: Typed
Requires-Dist: reverse-argparse
Requires-Dist: rich
Requires-Dist: tenacity
Project-URL: CI, https://github.com/sandialabs/staged-script/actions
Project-URL: Documentation, https://staged-script.readthedocs.io
Project-URL: Issues, https://github.com/sandialabs/staged-script/issues
Project-URL: Repository, https://github.com/sandialabs/staged-script
